{"@jumbotron-heading-color":"#d4916a","@body-bg":"#ffc9aa","@jumbotron-bg":"#551f00","@jumbotron-color":"#aa6239","@headings-color":"#551f00","@state-base-bg":"#aa6239","@link-color":"#d4916a","@well-base-bg":"#aa6239","@blockquote-border-color":"#551f00","@blockquote-small-color":"#aa6239","@hr-border":"#551f00","@btn-default-bg":"#d4916a","@btn-default-color":"#000000","@btn-primary-color":"#aa6239","@btn-primary-bg":"#551f00","@nav-pills-active-link-hover-bg":"#803c15","@nav-pills-active-link-hover-color":"#d4916a","@nav-link-hover-bg":"#aa6239","@nav-open-link-hover-color":"#ffc9aa","@nav-tabs-border-color":"#551f00","@nav-tabs-link-hover-border-color":"#551f00","@nav-tabs-active-link-hover-bg":"#803c15","@nav-tabs-active-link-hover-color":"#d4916a","@link-hover-color":"#803c15","@nav-tabs-active-link-hover-border-color":"#551f00","@table-border-color":"#551f00","@table-bg-accent":"#aa6239","@table-bg-hover":"#aa6239","@table-bg-active":"#aa6239","@table-bg":"#d4916a","@nav-tabs-justified-active-link-border-color":"#551f00","@nav-tabs-justified-link-border-color":"#551f00","@input-bg":"#551f00","@input-color":"#ffffff","@input-color-placeholder":"#ffffff","@input-group-addon-bg":"#aa6239","@input-group-addon-border-color":"#803c15","@input-border":"#803c15","@input-border-focus":"#ff9300","@input-bg-disabled":"#ffc9aa","@legend-color":"#aa6239","@legend-border-color":"#803c15","@panel-footer-bg":"#d4916a","@state-default-border":"#803c15","@state-default-bg":"#d4916a","@brand-primary":"#551f00","@state-primary-bg":"#551f00","@state-primary-text":"#d4916a","@dropdown-bg":"#803c15","@dropdown-header-color":"#ffc9aa","@dropdown-border":"#551f00","@dropdown-divider-bg":"#551f00","@dropdown-link-color":"#aa6239","@dropdown-link-disabled-color":"#551f00","@dropdown-link-hover-bg":"#d4916a","@dropdown-link-hover-color":"#551f00","@dropdown-link-active-color":"#ffc9aa","@pagination-bg":"#803c15","@pagination-color":"#aa6239","@pagination-border":"#551f00","@pagination-hover-bg":"#ffc9aa","@pagination-active-color":"#ffc9aa","@pagination-hover-border":"#000000","@pagination-hover-color":"#803c15","@pagination-disabled-color":"#803c15","@pagination-disabled-bg":"#551f00","@pagination-disabled-border":"#000000","@pagination-active-border":"#000000","@pager-disabled-color":"#551f00","@breadcrumb-bg":"#551f00","@breadcrumb-color":"#d4916a","@breadcrumb-active-color":"#ffc9aa","@thumbnail-bg":"#d4916a","@thumbnail-border":"#803c15","@thumbnail-caption-color":"#803c15","@label-primary-bg":"#551f00","@label-default-bg":"#d4916a","@popover-title-bg":"#803c15","@popover-arrow-color":"#aa6239","@modal-content-bg":"#d4916a","@modal-footer-border-color":"#551f00","@modal-header-border-color":"#551f00","@pre-bg":"#551f00","@pre-border-color":"#803c15","@pre-color":"#ffffff","@list-group-border":"#551f00","@list-group-link-heading-color":"#d4916a","@list-group-link-color":"#ffc9aa","@list-group-hover-bg":"#803c15","@list-group-active-color":"#d4916a","@list-group-active-text-color":"#aa6239"}